streamtask/__init__.py
streamtask/streamtask.py
streamtask/version.py
streamtask-0.0.9.dist-info/METADATA
streamtask-0.0.9.dist-info/WHEEL
streamtask-0.0.9.dist-info/top_level.txt
streamtask-0.0.9.dist-info/RECORD
