Metadata-Version: 2.1
Name: streamtask
Version: 0.0.9
Summary: Parallel Stream Task for Python
Home-page: https://github.com/fuzihaofzh/streamtask
Author: 
Author-email: 
License: UNKNOWN
Keywords: Parallel Stream Task
Platform: UNKNOWN
Classifier: Programming Language :: Python :: 3.7
Requires-Dist: tqdm
